opensrs
