Metadata-Version: 1.0
Name: OpenSRS
Version: 0.1.4
Summary: Higher level Python interface to the OpenSRS XML API
Home-page: https://github.com/fatbox/OpenSRS-py
Author: Evan Borgstrom
Author-email: evan@fatbox.ca
License: UNKNOWN
Platform: UNKNOWN
Classifier: Development Status :: 4 - Beta
Classifier: Intended Audience :: Developers
Classifier: License :: OSI Approved :: BSD License
Classifier: Natural Language :: English
Classifier: Topic :: Software Development :: Libraries
Classifier: Topic :: Software Development :: Libraries :: Python Modules
